setup.py
AMQPDeliver.egg-info/PKG-INFO
AMQPDeliver.egg-info/SOURCES.txt
AMQPDeliver.egg-info/dependency_links.txt
AMQPDeliver.egg-info/entry_points.txt
AMQPDeliver.egg-info/not-zip-safe
AMQPDeliver.egg-info/requires.txt
AMQPDeliver.egg-info/top_level.txt
amqpdeliver/__init__.py
amqpdeliver/hg.py
amqpdeliver/receive_d.py
amqpdeliver/send.py