Metadata-Version: 1.0
Name: AMQPDeliver
Version: 0.1
Summary: Asynchronous file transfer using AMQP
Home-page: http://www.lshift.net/
Author: David Ireland
Author-email: david@lshift.net
License: BSD
Download-URL: http://www.lshift.net/
Platform: UNKNOWN
Classifier: Intended Audience :: Developers
Classifier: License :: OSI Approved :: BSD License
Classifier: Operating System :: Unix
Classifier: Programming Language :: Python
Classifier: Topic :: Software Development :: Bug Tracking
Classifier: Topic :: Software Development :: Version Control
